DESCRIPTION.rst
MANIFEST.in
README.rst
setup.cfg
setup.py
pyonapp/__init__.py
pyonapp/onappapi.py
pyonapp/onappcli.py
pyonapp/resources.py
pyonapp.egg-info/PKG-INFO
pyonapp.egg-info/SOURCES.txt
pyonapp.egg-info/dependency_links.txt
pyonapp.egg-info/entry_points.txt
pyonapp.egg-info/requires.txt
pyonapp.egg-info/top_level.txt