Metadata-Version: 1.1
Name: pyonapp
Version: 1.1.1
Summary: python interface to onapp servers
Home-page: https://github.com/ZUNbado/pyonapp
Author: Marti Cardus
Author-email: marti@acs.li
License: GPL
Keywords: onapp api
Platform: UNKNOWN
Classifier: Development Status :: 3 - Alpha
Classifier: Intended Audience :: Developers
Classifier: Topic :: Software Development :: Build Tools
Classifier: Programming Language :: Python :: 2
Classifier: Programming Language :: Python :: 2.6
Classifier: Programming Language :: Python :: 2.7
Classifier: Programming Language :: Python :: 3
Classifier: Programming Language :: Python :: 3.2
Classifier: Programming Language :: Python :: 3.3
Classifier: Programming Language :: Python :: 3.4
